PyTweetToolkit/__init__.py
PyTweetToolkit/main.py
PyTweetToolkit/api/__init__.py
PyTweetToolkit/api/auth.py
PyTweetToolkit/api/bookmark.py
PyTweetToolkit/api/friendship.py
PyTweetToolkit/api/interaction.py
PyTweetToolkit/api/notification.py
PyTweetToolkit/api/profile.py
PyTweetToolkit/api/restrictions.py
PyTweetToolkit/api/search.py
PyTweetToolkit/api/tweet.py
PyTweetToolkit/api/upload.py
PyTweetToolkit/api/user.py
PyTweetToolkit/models/__init__.py
PyTweetToolkit/models/list_model.py
PyTweetToolkit/models/notification_model.py
PyTweetToolkit/models/tweet_model.py
PyTweetToolkit/models/user_model.py
PyTweetToolkit/utils/__init__.py
PyTweetToolkit/utils/request_handler.py
PyTweetToolkit-1.0.2.dist-info/LICENSE
PyTweetToolkit-1.0.2.dist-info/METADATA
PyTweetToolkit-1.0.2.dist-info/WHEEL
PyTweetToolkit-1.0.2.dist-info/top_level.txt
PyTweetToolkit-1.0.2.dist-info/RECORD
