Metadata-Version: 2.1
Name: PyTweetToolkit
Version: 1.0.2
Summary: PyTweetToolkit: An intuitive Python library for managing Twitter interactions, providing tools for posting tweets, engaging with users, and analyzing social media metrics. Perfect for automating tasks and integrating Twitter functionality into Python projects.
Home-page: https://github.com/DavyJonesCodes/PyTweetToolkit
Author: Dev Jones
Author-email: yashdhankhar5656@gmail.com
Classifier: Programming Language :: Python :: 3
Classifier: License :: OSI Approved :: MIT License
Classifier: Operating System :: OS Independent
Requires-Python: >=3.9
License-File: LICENSE
Requires-Dist: pillow>=10.2.0
Requires-Dist: requests>=2.31.0
